borco_scikit_build_core_example/__init__.py
borco_scikit_build_core_example/_core.cp312-win_amd64.pyd
borco_scikit_build_core_example/_core.pyi
borco_scikit_build_core_example-0.0.5.dist-info/METADATA
borco_scikit_build_core_example-0.0.5.dist-info/WHEEL
borco_scikit_build_core_example-0.0.5.dist-info/RECORD
