Metadata-Version: 2.1
Name: borco-scikit-build-core-example
Version: 0.0.5
Summary: Example package using scikit-build-core and Qt6
Author-Email: =?utf-8?q?Ioan_C=C4=83lin?= <iborco@gmail.com>
Requires-Python: >=3.12
